{
  "@context": {
    "entity": "https://vr.matcha.uno/entity/",
    "rdfs": "http://www.w3.org/2000/01/rdf-schema#",
    "schema": "https://schema.org/",
    "vr": "https://vr.matcha.uno/terms#"
  },
  "@graph": [
    {
      "@id": "vr:Prohibited",
      "rdfs:label": "不許可"
    },
    {
      "@id": "vr:ProhibitedExceptForPrivateUse",
      "rdfs:label": "私的利用を除き不許可"
    },
    {
      "@id": "entity:2215270",
      "rdfs:label": "薄荷 オリジナル3Dモデル #Hakka3D",
      "schema:license": {
        "@id": "https://avatar.mio3io.com/license/ja.pdf"
      },
      "schema:name": "薄荷",
      "schema:url": {
        "@id": "https://booth.pm/ja/items/2215270"
      }
    },
    {
      "@id": "https://avatar.mio3io.com/license/ja.pdf",
      "schema:isBasedOn": {
        "@id": "https://www.vn3.org/terms"
      },
      "vr:political": {
        "@id": "vr:Prohibited"
      },
      "vr:sexual": {
        "@id": "vr:ProhibitedExceptForPrivateUse"
      },
      "vr:violent": {
        "@id": "vr:ProhibitedExceptForPrivateUse"
      }
    }
  ]
}